machine_operator/__init__.py
machine_operator/oven.pymo
machine_operator/state_machine.py
machine_operator/state_machine.tx
machineop-0.1.0.dist-info/METADATA
machineop-0.1.0.dist-info/WHEEL
machineop-0.1.0.dist-info/entry_points.txt
machineop-0.1.0.dist-info/top_level.txt
machineop-0.1.0.dist-info/RECORD
